tkclasswiz/__init__.py
tkclasswiz/aliasing.py
tkclasswiz/annotations.py
tkclasswiz/cache.py
tkclasswiz/convert.py
tkclasswiz/deprecation.py
tkclasswiz/doc.py
tkclasswiz/dpi.py
tkclasswiz/extensions.py
tkclasswiz/messagebox.py
tkclasswiz/storage.py
tkclasswiz/utilities.py
tkclasswiz/object_frame/__init__.py
tkclasswiz/object_frame/frame_base.py
tkclasswiz/object_frame/frame_flag.py
tkclasswiz/object_frame/frame_iterable.py
tkclasswiz/object_frame/frame_number.py
tkclasswiz/object_frame/frame_string.py
tkclasswiz/object_frame/frame_struct.py
tkclasswiz/object_frame/tooltip.py
tkclasswiz/object_frame/window.py
TkClassWiz-1.4.10.dist-info/LICENSE
TkClassWiz-1.4.10.dist-info/METADATA
TkClassWiz-1.4.10.dist-info/WHEEL
TkClassWiz-1.4.10.dist-info/top_level.txt
TkClassWiz-1.4.10.dist-info/RECORD
