Metadata-Version: 2.1
Name: TkClassWiz
Version: 1.4.10
Summary: Library for graphically defining objects based on class annotations. Works with Tkinter / TTKBootstrap
Author: David Hozic
Keywords: Tkinter,TTKBootstrap,Python3,ObjectDef,ClassWiz,ClassWiz,GUI
Classifier: Programming Language :: Python :: 3
Classifier: License :: OSI Approved :: MIT License
Classifier: Operating System :: OS Independent
Requires-Python: >=3.9
License-File: LICENSE
Provides-Extra: docs
Requires-Dist: sphinx ~=7.2.6 ; extra == 'docs'
Requires-Dist: sphinx-autobuild ==2021.3.14 ; extra == 'docs'
Requires-Dist: sphinx-copybutton ~=0.5.2 ; extra == 'docs'
Requires-Dist: furo ==2023.9.10 ; extra == 'docs'
Requires-Dist: enum-tools[sphinx] ~=0.11.0 ; extra == 'docs'
Requires-Dist: sphinx-design[furo] ~=0.5.0 ; extra == 'docs'
Requires-Dist: readthedocs-sphinx-search ~=0.3.2 ; extra == 'docs'
Requires-Dist: sphinxcontrib-svg2pdfconverter ~=1.2.2 ; extra == 'docs'
